<customView xmlns="http://labkey.org/data/xml/queryCustomView">
   <columns>
       <column name="Id" />
       <column name="date" />
       <column name="project" />
       <column name="project/protocol"/>
       <column name="quantity" />
       <column name="tube_type" />
       <column name="additionalServices" />
       <column name="remark" />
       <column name="sampletype" />
       <column name="reason"/>
       <column name="chargetype" />
       <column name="qcstate" />
       <column name="taskid" />
       <column name="requestid" />
    </columns>
   <sorts>
       <sort column="date" descending="true"/>
       <sort column="Id" />
   </sorts>
    <!--<filters>-->
        <!--<filter column="qcstate/publicdata" operator="eq" value="true"/>-->
    <!--</filters>-->
</customView>